Metadata-Version: 1.0
Name: prob-distribution-dsnd
Version: 0.1
Summary: Gaussian and Binomial distributions
Home-page: UNKNOWN
Author: Amaefula Maryann
Author-email: amaannmary006@gmail.com
License: UNKNOWN
Platform: UNKNOWN
